cozypy/__init__.py
cozypy/client.py
cozypy/constant.py
cozypy/exception.py
cozypy/handlers.py
cozypy/objects.py
cozypy/utils.py
cozypy-1.2.7.dist-info/LICENSE
cozypy-1.2.7.dist-info/METADATA
cozypy-1.2.7.dist-info/WHEEL
cozypy-1.2.7.dist-info/top_level.txt
cozypy-1.2.7.dist-info/RECORD
